antigravity_remote/__init__.py
antigravity_remote/__main__.py
antigravity_remote/agent.py
antigravity_remote/bot.py
antigravity_remote/config.py
antigravity_remote/secrets.py
antigravity_remote/state.py
antigravity_remote/two_way_chat.py
antigravity_remote/handlers/__init__.py
antigravity_remote/handlers/ai.py
antigravity_remote/handlers/base.py
antigravity_remote/handlers/control.py
antigravity_remote/handlers/files.py
antigravity_remote/handlers/monitoring.py
antigravity_remote/handlers/quick.py
antigravity_remote/handlers/screen.py
antigravity_remote/utils/__init__.py
antigravity_remote/utils/automation.py
antigravity_remote/utils/ocr.py
antigravity_remote/utils/screenshot.py
antigravity_remote-4.6.1.dist-info/METADATA
antigravity_remote-4.6.1.dist-info/WHEEL
antigravity_remote-4.6.1.dist-info/entry_points.txt
antigravity_remote-4.6.1.dist-info/licenses/LICENSE
antigravity_remote-4.6.1.dist-info/RECORD
