Metadata-Version: 2.4
Name: antigravity-remote
Version: 4.6.1
Summary: The Vibecoder's Best Friend - Control your AI coding assistant from your phone
Project-URL: Homepage, https://github.com/kubrat/antigravity-remote
Project-URL: Repository, https://github.com/kubrat/antigravity-remote
Author: Kubrat
License-Expression: MIT
License-File: LICENSE
Keywords: ai,antigravity,automation,bot,mobile-coding,remote,telegram,vibecoder
Classifier: Development Status :: 4 - Beta
Classifier: Environment :: Console
Classifier: Intended Audience :: Developers
Classifier: License :: OSI Approved :: MIT License
Classifier: Operating System :: Microsoft :: Windows
Classifier: Programming Language :: Python :: 3.10
Classifier: Programming Language :: Python :: 3.11
Classifier: Programming Language :: Python :: 3.12
Classifier: Programming Language :: Python :: 3.13
Classifier: Topic :: Communications :: Chat
Requires-Python: >=3.10
Requires-Dist: av>=10.0.0
Requires-Dist: fastapi>=0.95.0
Requires-Dist: httpx>=0.24.0
Requires-Dist: mss>=9.0.0
Requires-Dist: pillow>=10.0.0
Requires-Dist: psutil>=5.9.0
Requires-Dist: pyautogui>=0.9.53
Requires-Dist: pydantic>=2.0.0
Requires-Dist: pygetwindow>=0.0.9
Requires-Dist: pyperclip>=1.8.2
Requires-Dist: python-telegram-bot>=20.0
Requires-Dist: rich>=13.0.0
Requires-Dist: uvicorn>=0.21.0
Requires-Dist: websockets>=10.0
Provides-Extra: all
Requires-Dist: faster-whisper>=0.9.0; extra == 'all'
Requires-Dist: keyring>=23.0.0; extra == 'all'
Requires-Dist: pydub>=0.25.0; extra == 'all'
Requires-Dist: pyttsx3>=2.90; extra == 'all'
Provides-Extra: dev
Requires-Dist: black>=23.0.0; extra == 'dev'
Requires-Dist: httpx>=0.24.0; extra == 'dev'
Requires-Dist: mypy>=1.0.0; extra == 'dev'
Requires-Dist: pytest-asyncio>=0.21.0; extra == 'dev'
Requires-Dist: pytest-cov>=4.0.0; extra == 'dev'
Requires-Dist: pytest>=7.0.0; extra == 'dev'
Requires-Dist: ruff>=0.1.0; extra == 'dev'
Provides-Extra: secure
Requires-Dist: keyring>=23.0.0; extra == 'secure'
Provides-Extra: tts
Requires-Dist: pyttsx3>=2.90; extra == 'tts'
Provides-Extra: voice
Requires-Dist: faster-whisper>=0.9.0; extra == 'voice'
Requires-Dist: pydub>=0.25.0; extra == 'voice'
